setup.py
jupyterlab_tranquilblue_theme/_version.py
jupyterlab_tranquilblue_theme-0.1.1.data/data/share/jupyter/labextensions/jupyterlab_tranquilblue_theme/build_log.json
jupyterlab_tranquilblue_theme-0.1.1.data/data/share/jupyter/labextensions/jupyterlab_tranquilblue_theme/package.json
jupyterlab_tranquilblue_theme-0.1.1.data/data/share/jupyter/labextensions/jupyterlab_tranquilblue_theme/static/lib_index_js.7f81403fe1439f3e1862.js
jupyterlab_tranquilblue_theme-0.1.1.data/data/share/jupyter/labextensions/jupyterlab_tranquilblue_theme/static/lib_index_js.7f81403fe1439f3e1862.js.map
jupyterlab_tranquilblue_theme-0.1.1.data/data/share/jupyter/labextensions/jupyterlab_tranquilblue_theme/static/remoteEntry.3a44e7d5b9c544985cea.js
jupyterlab_tranquilblue_theme-0.1.1.data/data/share/jupyter/labextensions/jupyterlab_tranquilblue_theme/static/remoteEntry.3a44e7d5b9c544985cea.js.map
jupyterlab_tranquilblue_theme-0.1.1.data/data/share/jupyter/labextensions/jupyterlab_tranquilblue_theme/static/style.js
jupyterlab_tranquilblue_theme-0.1.1.data/data/share/jupyter/labextensions/jupyterlab_tranquilblue_theme/themes/jupyterlab_tranquilblue_theme/index.css
jupyterlab_tranquilblue_theme-0.1.1.data/data/share/jupyter/labextensions/jupyterlab_tranquilblue_theme/themes/jupyterlab_tranquilblue_theme/index.js
jupyterlab_tranquilblue_theme-0.1.1.data/data/share/jupyter/labextensions/jupyterlab_tranquilblue_theme/install.json
jupyterlab_tranquilblue_theme-0.1.1.dist-info/METADATA
jupyterlab_tranquilblue_theme-0.1.1.dist-info/WHEEL
jupyterlab_tranquilblue_theme-0.1.1.dist-info/licenses/LICENSE
jupyterlab_tranquilblue_theme-0.1.1.dist-info/RECORD
